freezegun/__init__.py
freezegun/_async.py
freezegun/api.py
freezegun/config.py
freezegun/py.typed
freezegun-1.5.0.dist-info/AUTHORS.rst
freezegun-1.5.0.dist-info/LICENSE
freezegun-1.5.0.dist-info/METADATA
freezegun-1.5.0.dist-info/WHEEL
freezegun-1.5.0.dist-info/top_level.txt
freezegun-1.5.0.dist-info/RECORD
