Metadata-Version: 2.1
Name: freezegun
Version: 1.5.0
Summary: Let your Python tests travel through time
Home-page: https://github.com/spulec/freezegun
Author: Steve Pulec
Author-email: spulec@gmail.com
License: Apache 2.0
Project-URL: Bug Tracker, https://github.com/spulec/freezegun/issues
Project-URL: Changes, https://github.com/spulec/freezegun/blob/master/CHANGELOG
Project-URL: Documentation, https://github.com/spulec/freezegun/blob/master/README.rst
Project-URL: Source Code, https://github.com/spulec/freezegun
Classifier: License :: OSI Approved :: Apache Software License
Classifier: Programming Language :: Python :: 3
Classifier: Programming Language :: Python :: 3.7
Classifier: Programming Language :: Python :: 3.8
Classifier: Programming Language :: Python :: 3.9
Classifier: Programming Language :: Python :: 3.10
Classifier: Programming Language :: Python :: 3.11
Classifier: Programming Language :: Python :: 3.12
Classifier: Programming Language :: Python :: Implementation :: CPython
Classifier: Programming Language :: Python :: Implementation :: PyPy
Requires-Python: >=3.7
License-File: LICENSE
License-File: AUTHORS.rst
Requires-Dist: python-dateutil>=2.7
